fastapi_swagger_auth/__init__.py
fastapi_swagger_auth/config.py
fastapi_swagger_auth/core.py
fastapi_swagger_auth/swagger_ui.py
fastapi_swagger_auth/providers/__init__.py
fastapi_swagger_auth/providers/base.py
fastapi_swagger_auth/providers/custom.py
fastapi_swagger_auth/providers/supabase.py
fastapi_swagger_auth-0.1.0.dist-info/licenses/LICENSE
fastapi_swagger_auth-0.1.0.dist-info/METADATA
fastapi_swagger_auth-0.1.0.dist-info/WHEEL
fastapi_swagger_auth-0.1.0.dist-info/top_level.txt
fastapi_swagger_auth-0.1.0.dist-info/RECORD
