Metadata-Version: 2.4
Name: fastapi-swagger-auth
Version: 0.1.0
Summary: Automatic Swagger UI authentication for FastAPI development
Author-email: Max Falkowitz <max@example.com>
License: MIT
Project-URL: Homepage, https://github.com/maxfalkowitz/fastapi-swagger-auth
Project-URL: Bug Tracker, https://github.com/maxfalkowitz/fastapi-swagger-auth/issues
Keywords: fastapi,swagger,authentication,jwt,development
Classifier: Development Status :: 3 - Alpha
Classifier: Intended Audience :: Developers
Classifier: License :: OSI Approved :: MIT License
Classifier: Programming Language :: Python :: 3
Classifier: Programming Language :: Python :: 3.8
Classifier: Programming Language :: Python :: 3.9
Classifier: Programming Language :: Python :: 3.10
Classifier: Programming Language :: Python :: 3.11
Classifier: Programming Language :: Python :: 3.12
Classifier: Framework :: FastAPI
Requires-Python: >=3.8
License-File: LICENSE
Requires-Dist: fastapi>=0.100.0
Requires-Dist: python-jose[cryptography]>=3.3.0
Requires-Dist: httpx>=0.24.0
Provides-Extra: supabase
Requires-Dist: supabase>=2.0.0; extra == "supabase"
Provides-Extra: dev
Requires-Dist: pytest>=7.0.0; extra == "dev"
Requires-Dist: pytest-asyncio>=0.21.0; extra == "dev"
Requires-Dist: ruff>=0.1.0; extra == "dev"
Requires-Dist: build>=1.0.0; extra == "dev"
Requires-Dist: twine>=4.0.0; extra == "dev"
Dynamic: license-file
